api/__init__.py
api/bypass.py
api/chatgpt.py
api/imageai.py
cooldowns/__init__.py
cooldowns/cooldown_manager.py
TestHub-0.1.9.dist-info/LICENSE
TestHub-0.1.9.dist-info/METADATA
TestHub-0.1.9.dist-info/WHEEL
TestHub-0.1.9.dist-info/top_level.txt
TestHub-0.1.9.dist-info/RECORD
