Metadata-Version: 2.2
Name: TestHub
Version: 0.1.9
Author: Dearygt.
Requires-Python: >=3.6
License-File: LICENSE
Requires-Dist: requests
Dynamic: author
Dynamic: requires-dist
Dynamic: requires-python
